<?xml version="1.0" encoding="UTF-8"?>
<MetaDataObject xmlns="http://v8.1c.ru/8.3/MDClasses" xmlns:app="http://v8.1c.ru/8.2/managed-application/core" xmlns:cfg="http://v8.1c.ru/8.1/data/enterprise/current-config" xmlns:cmi="http://v8.1c.ru/8.2/managed-application/cmi" xmlns:ent="http://v8.1c.ru/8.1/data/enterprise" xmlns:lf="http://v8.1c.ru/8.2/managed-application/logform" xmlns:style="http://v8.1c.ru/8.1/data/ui/style" xmlns:sys="http://v8.1c.ru/8.1/data/ui/fonts/system" xmlns:v8="http://v8.1c.ru/8.1/data/core" xmlns:v8ui="http://v8.1c.ru/8.1/data/ui" xmlns:web="http://v8.1c.ru/8.1/data/ui/colors/web" xmlns:win="http://v8.1c.ru/8.1/data/ui/colors/windows" xmlns:xen="http://v8.1c.ru/8.3/xcf/enums" xmlns:xpr="http://v8.1c.ru/8.3/xcf/predef" xmlns:xr="http://v8.1c.ru/8.3/xcf/readable" xmlns:xs="http://www.w3.org/2001/XMLSchema" xmlns:xsi="http://www.w3.org/2001/XMLSchema-instance">
	<DataProcessor uuid="6084e75c-e19f-4a09-a285-bf631fcecd4a">
		<InnerInfo>
			<xr:producedType name="DataProcessorObject.Pack_Unpack_1с" category="Object">
				<xr:typeId>9c0f9975-8c0e-4c91-b8ad-9f0d242ac233</xr:typeId>
				<xr:valTypeId>7d8c6168-51b8-45c5-9209-bad99c749f64</xr:valTypeId>
			</xr:producedType>
			<xr:producedType name="DataProcessorManager.Pack_Unpack_1с" category="Manager">
				<xr:typeId>16902e87-dd91-4a4d-a182-c4f4dad2eab3</xr:typeId>
				<xr:valTypeId>d52b2d54-ea5c-46fe-b54c-fc7c0c6f7504</xr:valTypeId>
			</xr:producedType>
		</InnerInfo>
		<Properties>
			<Name>Pack_Unpack_1с</Name>
			<Synonym>
				<v8:item>
					<v8:lang>ru</v8:lang>
					<v8:content>Преобразования файлов конфигурации</v8:content>
				</v8:item>
			</Synonym>
			<Comment/>
			<UseStandardCommands>true</UseStandardCommands>
			<DefaultForm>DataProcessor.Pack_Unpack_1с.Form.Форма</DefaultForm>
			<AuxiliaryForm/>
			<IncludeHelpInContents>false</IncludeHelpInContents>
			<ExtendedPresentation/>
			<Explanation/>
		</Properties>
		<ChildObjects>
			<Attribute uuid="7e29948f-86f9-45c1-a396-49e1b5f55d54">
				<Properties>
					<Name>Директория</Name>
					<Synonym>
						<v8:item>
							<v8:lang>ru</v8:lang>
							<v8:content>Директория</v8:content>
						</v8:item>
					</Synonym>
					<Comment/>
					<Type>
						<v8:Type>xs:string</v8:Type>
						<v8:StringQualifiers>
							<v8:Length>0</v8:Length>
							<v8:AllowedLength>Variable</v8:AllowedLength>
						</v8:StringQualifiers>
					</Type>
					<PasswordMode>false</PasswordMode>
					<Format/>
					<EditFormat/>
					<ToolTip/>
					<MarkNegatives>false</MarkNegatives>
					<Mask/>
					<MultiLine>false</MultiLine>
					<ExtendedEdit>false</ExtendedEdit>
					<MinValue xsi:nil="true"/>
					<MaxValue xsi:nil="true"/>
					<FillChecking>DontCheck</FillChecking>
					<ChoiceFoldersAndItems>Items</ChoiceFoldersAndItems>
					<ChoiceParameterLinks/>
					<ChoiceParameters/>
					<QuickChoice>Auto</QuickChoice>
					<CreateOnInput>Auto</CreateOnInput>
					<ChoiceForm/>
					<LinkByType/>
					<ChoiceHistoryOnInput>Auto</ChoiceHistoryOnInput>
				</Properties>
			</Attribute>
			<TabularSection uuid="6e76a4be-a4d2-4270-a16a-d09b42c03cd9">
				<InnerInfo>
					<xr:producedType name="DataProcessorTabularSection.Pack_Unpack_1с.Файлы" category="TabularSection">
						<xr:typeId>5288c7f6-9fe6-41c1-9999-6376ce97168d</xr:typeId>
						<xr:valTypeId>fec8b385-a51a-4f97-9d80-3bf59115f9dc</xr:valTypeId>
					</xr:producedType>
					<xr:producedType name="DataProcessorTabularSectionRow.Pack_Unpack_1с.Файлы" category="TabularSectionRow">
						<xr:typeId>258df2a4-da5a-4034-9a77-b857751706a5</xr:typeId>
						<xr:valTypeId>a4a98109-1137-4b1a-b365-d4a0647b0431</xr:valTypeId>
					</xr:producedType>
				</InnerInfo>
				<Properties>
					<Name>Файлы</Name>
					<Synonym>
						<v8:item>
							<v8:lang>ru</v8:lang>
							<v8:content>Файлы</v8:content>
						</v8:item>
					</Synonym>
					<Comment/>
					<ToolTip/>
					<FillChecking>DontCheck</FillChecking>
					<StandardAttributes>
						<xr:Attribute name="LineNumber">
							<xr:LinkByType/>
							<xr:FillChecking>DontCheck</xr:FillChecking>
							<xr:MultiLine>false</xr:MultiLine>
							<xr:FillFromFillingValue>false</xr:FillFromFillingValue>
							<xr:CreateOnInput>Auto</xr:CreateOnInput>
							<xr:MaxValue xsi:nil="true"/>
							<xr:ToolTip/>
							<xr:ExtendedEdit>false</xr:ExtendedEdit>
							<xr:Format/>
							<xr:ChoiceForm/>
							<xr:QuickChoice>Auto</xr:QuickChoice>
							<xr:ChoiceHistoryOnInput>Auto</xr:ChoiceHistoryOnInput>
							<xr:EditFormat/>
							<xr:PasswordMode>false</xr:PasswordMode>
							<xr:MarkNegatives>false</xr:MarkNegatives>
							<xr:MinValue xsi:nil="true"/>
							<xr:Synonym/>
							<xr:Comment/>
							<xr:FullTextSearch>Use</xr:FullTextSearch>
							<xr:ChoiceParameterLinks/>
							<xr:FillValue xsi:nil="true"/>
							<xr:Mask/>
							<xr:ChoiceParameters/>
						</xr:Attribute>
					</StandardAttributes>
				</Properties>
				<ChildObjects>
					<Attribute uuid="47511914-29f1-4a75-9de3-efb37850ae49">
						<Properties>
							<Name>ИмяФайла</Name>
							<Synonym>
								<v8:item>
									<v8:lang>ru</v8:lang>
									<v8:content>Имя файла</v8:content>
								</v8:item>
							</Synonym>
							<Comment/>
							<Type>
								<v8:Type>xs:string</v8:Type>
								<v8:StringQualifiers>
									<v8:Length>0</v8:Length>
									<v8:AllowedLength>Variable</v8:AllowedLength>
								</v8:StringQualifiers>
							</Type>
							<PasswordMode>false</PasswordMode>
							<Format/>
							<EditFormat/>
							<ToolTip/>
							<MarkNegatives>false</MarkNegatives>
							<Mask/>
							<MultiLine>false</MultiLine>
							<ExtendedEdit>false</ExtendedEdit>
							<MinValue xsi:nil="true"/>
							<MaxValue xsi:nil="true"/>
							<FillFromFillingValue>false</FillFromFillingValue>
							<FillValue xsi:type="xs:string"/>
							<FillChecking>DontCheck</FillChecking>
							<ChoiceFoldersAndItems>Items</ChoiceFoldersAndItems>
							<ChoiceParameterLinks/>
							<ChoiceParameters/>
							<QuickChoice>Auto</QuickChoice>
							<CreateOnInput>Auto</CreateOnInput>
							<ChoiceForm/>
							<LinkByType/>
							<ChoiceHistoryOnInput>Auto</ChoiceHistoryOnInput>
						</Properties>
					</Attribute>
					<Attribute uuid="64b83479-564c-41f3-8f88-759435f41576">
						<Properties>
							<Name>Каталог</Name>
							<Synonym>
								<v8:item>
									<v8:lang>ru</v8:lang>
									<v8:content>Каталог</v8:content>
								</v8:item>
							</Synonym>
							<Comment/>
							<Type>
								<v8:Type>xs:string</v8:Type>
								<v8:StringQualifiers>
									<v8:Length>0</v8:Length>
									<v8:AllowedLength>Variable</v8:AllowedLength>
								</v8:StringQualifiers>
							</Type>
							<PasswordMode>false</PasswordMode>
							<Format/>
							<EditFormat/>
							<ToolTip/>
							<MarkNegatives>false</MarkNegatives>
							<Mask/>
							<MultiLine>false</MultiLine>
							<ExtendedEdit>false</ExtendedEdit>
							<MinValue xsi:nil="true"/>
							<MaxValue xsi:nil="true"/>
							<FillFromFillingValue>false</FillFromFillingValue>
							<FillValue xsi:type="xs:string"/>
							<FillChecking>DontCheck</FillChecking>
							<ChoiceFoldersAndItems>Items</ChoiceFoldersAndItems>
							<ChoiceParameterLinks/>
							<ChoiceParameters/>
							<QuickChoice>Auto</QuickChoice>
							<CreateOnInput>Auto</CreateOnInput>
							<ChoiceForm/>
							<LinkByType/>
							<ChoiceHistoryOnInput>Auto</ChoiceHistoryOnInput>
						</Properties>
					</Attribute>
					<Attribute uuid="3b97ce3a-21b1-48df-a3e8-780e9c7223ee">
						<Properties>
							<Name>НовоеИмя</Name>
							<Synonym>
								<v8:item>
									<v8:lang>ru</v8:lang>
									<v8:content>Новое имя</v8:content>
								</v8:item>
							</Synonym>
							<Comment/>
							<Type>
								<v8:Type>xs:string</v8:Type>
								<v8:StringQualifiers>
									<v8:Length>0</v8:Length>
									<v8:AllowedLength>Variable</v8:AllowedLength>
								</v8:StringQualifiers>
							</Type>
							<PasswordMode>false</PasswordMode>
							<Format/>
							<EditFormat/>
							<ToolTip/>
							<MarkNegatives>false</MarkNegatives>
							<Mask/>
							<MultiLine>false</MultiLine>
							<ExtendedEdit>false</ExtendedEdit>
							<MinValue xsi:nil="true"/>
							<MaxValue xsi:nil="true"/>
							<FillFromFillingValue>false</FillFromFillingValue>
							<FillValue xsi:type="xs:string"/>
							<FillChecking>DontCheck</FillChecking>
							<ChoiceFoldersAndItems>Items</ChoiceFoldersAndItems>
							<ChoiceParameterLinks/>
							<ChoiceParameters/>
							<QuickChoice>Auto</QuickChoice>
							<CreateOnInput>Auto</CreateOnInput>
							<ChoiceForm/>
							<LinkByType/>
							<ChoiceHistoryOnInput>Auto</ChoiceHistoryOnInput>
						</Properties>
					</Attribute>
					<Attribute uuid="412de9d5-4464-4dc8-8b4c-ff999cbc082f">
						<Properties>
							<Name>Обработано</Name>
							<Synonym>
								<v8:item>
									<v8:lang>ru</v8:lang>
									<v8:content>Обработано</v8:content>
								</v8:item>
							</Synonym>
							<Comment/>
							<Type>
								<v8:Type>xs:boolean</v8:Type>
							</Type>
							<PasswordMode>false</PasswordMode>
							<Format/>
							<EditFormat/>
							<ToolTip/>
							<MarkNegatives>false</MarkNegatives>
							<Mask/>
							<MultiLine>false</MultiLine>
							<ExtendedEdit>false</ExtendedEdit>
							<MinValue xsi:nil="true"/>
							<MaxValue xsi:nil="true"/>
							<FillFromFillingValue>false</FillFromFillingValue>
							<FillValue xsi:nil="true"/>
							<FillChecking>DontCheck</FillChecking>
							<ChoiceFoldersAndItems>Items</ChoiceFoldersAndItems>
							<ChoiceParameterLinks/>
							<ChoiceParameters/>
							<QuickChoice>Auto</QuickChoice>
							<CreateOnInput>Auto</CreateOnInput>
							<ChoiceForm/>
							<LinkByType/>
							<ChoiceHistoryOnInput>Auto</ChoiceHistoryOnInput>
						</Properties>
					</Attribute>
				</ChildObjects>
			</TabularSection>
			<TabularSection uuid="62d5dc3d-13e0-46fc-a5f0-376c5f6a52cb">
				<InnerInfo>
					<xr:producedType name="DataProcessorTabularSection.Pack_Unpack_1с.БазыДанных" category="TabularSection">
						<xr:typeId>3cdf5f1d-44f0-4e08-9c97-ec8de1060775</xr:typeId>
						<xr:valTypeId>d1d67204-87cc-4f07-8c5e-0b485323ef77</xr:valTypeId>
					</xr:producedType>
					<xr:producedType name="DataProcessorTabularSectionRow.Pack_Unpack_1с.БазыДанных" category="TabularSectionRow">
						<xr:typeId>7939153e-bdae-44ee-853f-7586b1503a54</xr:typeId>
						<xr:valTypeId>a4e67b9f-881b-4317-a403-653806b1dbed</xr:valTypeId>
					</xr:producedType>
				</InnerInfo>
				<Properties>
					<Name>БазыДанных</Name>
					<Synonym>
						<v8:item>
							<v8:lang>ru</v8:lang>
							<v8:content>Базы данных</v8:content>
						</v8:item>
					</Synonym>
					<Comment/>
					<ToolTip/>
					<FillChecking>DontCheck</FillChecking>
					<StandardAttributes>
						<xr:Attribute name="LineNumber">
							<xr:LinkByType/>
							<xr:FillChecking>DontCheck</xr:FillChecking>
							<xr:MultiLine>false</xr:MultiLine>
							<xr:FillFromFillingValue>false</xr:FillFromFillingValue>
							<xr:CreateOnInput>Auto</xr:CreateOnInput>
							<xr:MaxValue xsi:nil="true"/>
							<xr:ToolTip/>
							<xr:ExtendedEdit>false</xr:ExtendedEdit>
							<xr:Format/>
							<xr:ChoiceForm/>
							<xr:QuickChoice>Auto</xr:QuickChoice>
							<xr:ChoiceHistoryOnInput>Auto</xr:ChoiceHistoryOnInput>
							<xr:EditFormat/>
							<xr:PasswordMode>false</xr:PasswordMode>
							<xr:MarkNegatives>false</xr:MarkNegatives>
							<xr:MinValue xsi:nil="true"/>
							<xr:Synonym/>
							<xr:Comment/>
							<xr:FullTextSearch>Use</xr:FullTextSearch>
							<xr:ChoiceParameterLinks/>
							<xr:FillValue xsi:nil="true"/>
							<xr:Mask/>
							<xr:ChoiceParameters/>
						</xr:Attribute>
					</StandardAttributes>
				</Properties>
				<ChildObjects>
					<Attribute uuid="625f334a-a93f-4036-93b8-86367196459e">
						<Properties>
							<Name>Наименование</Name>
							<Synonym>
								<v8:item>
									<v8:lang>ru</v8:lang>
									<v8:content>Наименование</v8:content>
								</v8:item>
							</Synonym>
							<Comment/>
							<Type>
								<v8:Type>xs:string</v8:Type>
								<v8:StringQualifiers>
									<v8:Length>0</v8:Length>
									<v8:AllowedLength>Variable</v8:AllowedLength>
								</v8:StringQualifiers>
							</Type>
							<PasswordMode>false</PasswordMode>
							<Format/>
							<EditFormat/>
							<ToolTip/>
							<MarkNegatives>false</MarkNegatives>
							<Mask/>
							<MultiLine>false</MultiLine>
							<ExtendedEdit>false</ExtendedEdit>
							<MinValue xsi:nil="true"/>
							<MaxValue xsi:nil="true"/>
							<FillFromFillingValue>false</FillFromFillingValue>
							<FillValue xsi:type="xs:string"/>
							<FillChecking>DontCheck</FillChecking>
							<ChoiceFoldersAndItems>Items</ChoiceFoldersAndItems>
							<ChoiceParameterLinks/>
							<ChoiceParameters/>
							<QuickChoice>Auto</QuickChoice>
							<CreateOnInput>Auto</CreateOnInput>
							<ChoiceForm/>
							<LinkByType/>
							<ChoiceHistoryOnInput>Auto</ChoiceHistoryOnInput>
						</Properties>
					</Attribute>
					<Attribute uuid="43f5b863-0cab-4ae5-a09f-f7515a70d461">
						<Properties>
							<Name>СтрокаПодключения</Name>
							<Synonym>
								<v8:item>
									<v8:lang>ru</v8:lang>
									<v8:content>Строка подключения</v8:content>
								</v8:item>
							</Synonym>
							<Comment/>
							<Type>
								<v8:Type>xs:string</v8:Type>
								<v8:StringQualifiers>
									<v8:Length>0</v8:Length>
									<v8:AllowedLength>Variable</v8:AllowedLength>
								</v8:StringQualifiers>
							</Type>
							<PasswordMode>false</PasswordMode>
							<Format/>
							<EditFormat/>
							<ToolTip/>
							<MarkNegatives>false</MarkNegatives>
							<Mask/>
							<MultiLine>false</MultiLine>
							<ExtendedEdit>false</ExtendedEdit>
							<MinValue xsi:nil="true"/>
							<MaxValue xsi:nil="true"/>
							<FillFromFillingValue>false</FillFromFillingValue>
							<FillValue xsi:type="xs:string"/>
							<FillChecking>DontCheck</FillChecking>
							<ChoiceFoldersAndItems>Items</ChoiceFoldersAndItems>
							<ChoiceParameterLinks/>
							<ChoiceParameters/>
							<QuickChoice>Auto</QuickChoice>
							<CreateOnInput>Auto</CreateOnInput>
							<ChoiceForm/>
							<LinkByType/>
							<ChoiceHistoryOnInput>Auto</ChoiceHistoryOnInput>
						</Properties>
					</Attribute>
					<Attribute uuid="6cf22399-7ccc-44fa-9e6e-f6f6b7e0baf1">
						<Properties>
							<Name>Пользователь</Name>
							<Synonym>
								<v8:item>
									<v8:lang>ru</v8:lang>
									<v8:content>Пользователь</v8:content>
								</v8:item>
							</Synonym>
							<Comment/>
							<Type>
								<v8:Type>xs:string</v8:Type>
								<v8:StringQualifiers>
									<v8:Length>0</v8:Length>
									<v8:AllowedLength>Variable</v8:AllowedLength>
								</v8:StringQualifiers>
							</Type>
							<PasswordMode>false</PasswordMode>
							<Format/>
							<EditFormat/>
							<ToolTip/>
							<MarkNegatives>false</MarkNegatives>
							<Mask/>
							<MultiLine>false</MultiLine>
							<ExtendedEdit>false</ExtendedEdit>
							<MinValue xsi:nil="true"/>
							<MaxValue xsi:nil="true"/>
							<FillFromFillingValue>false</FillFromFillingValue>
							<FillValue xsi:type="xs:string"/>
							<FillChecking>DontCheck</FillChecking>
							<ChoiceFoldersAndItems>Items</ChoiceFoldersAndItems>
							<ChoiceParameterLinks/>
							<ChoiceParameters/>
							<QuickChoice>Auto</QuickChoice>
							<CreateOnInput>Auto</CreateOnInput>
							<ChoiceForm/>
							<LinkByType/>
							<ChoiceHistoryOnInput>Auto</ChoiceHistoryOnInput>
						</Properties>
					</Attribute>
					<Attribute uuid="6df8fcf5-3167-45ba-bb9b-3759891be258">
						<Properties>
							<Name>Пароль</Name>
							<Synonym>
								<v8:item>
									<v8:lang>ru</v8:lang>
									<v8:content>Пароль</v8:content>
								</v8:item>
							</Synonym>
							<Comment/>
							<Type>
								<v8:Type>xs:string</v8:Type>
								<v8:StringQualifiers>
									<v8:Length>0</v8:Length>
									<v8:AllowedLength>Variable</v8:AllowedLength>
								</v8:StringQualifiers>
							</Type>
							<PasswordMode>false</PasswordMode>
							<Format/>
							<EditFormat/>
							<ToolTip/>
							<MarkNegatives>false</MarkNegatives>
							<Mask/>
							<MultiLine>false</MultiLine>
							<ExtendedEdit>false</ExtendedEdit>
							<MinValue xsi:nil="true"/>
							<MaxValue xsi:nil="true"/>
							<FillFromFillingValue>false</FillFromFillingValue>
							<FillValue xsi:type="xs:string"/>
							<FillChecking>DontCheck</FillChecking>
							<ChoiceFoldersAndItems>Items</ChoiceFoldersAndItems>
							<ChoiceParameterLinks/>
							<ChoiceParameters/>
							<QuickChoice>Auto</QuickChoice>
							<CreateOnInput>Auto</CreateOnInput>
							<ChoiceForm/>
							<LinkByType/>
							<ChoiceHistoryOnInput>Auto</ChoiceHistoryOnInput>
						</Properties>
					</Attribute>
				</ChildObjects>
			</TabularSection>
			<Form>Форма</Form>
		</ChildObjects>
	</DataProcessor>
</MetaDataObject>